openghg_defs/__init__.py
openghg_defs/py.typed
openghg_defs/data/domain_info.json
openghg_defs/data/site_info.json
openghg_defs/data/species_info.json
openghg_defs/data/domain/ARCTIC_latitude.dat
openghg_defs/data/domain/ARCTIC_longitude.dat
openghg_defs/data/domain/EASTASIA_latitude.dat
openghg_defs/data/domain/EASTASIA_longitude.dat
openghg_defs/data/domain/EUROPE_latitude.dat
openghg_defs/data/domain/EUROPE_longitude.dat
openghg_defs/data/domain/PACIFIC_latitude.dat
openghg_defs/data/domain/PACIFIC_longitude.dat
openghg_defs/data/domain/SOUTHAFRICA_latitude.dat
openghg_defs/data/domain/SOUTHAFRICA_longitude.dat
openghg_defs/data/domain/USA_latitude.dat
openghg_defs/data/domain/USA_longitude.dat
openghg_defs-0.0.6.dist-info/licenses/LICENSE
recipes/meta.yaml
tests/test_valid.py
openghg_defs-0.0.6.dist-info/METADATA
openghg_defs-0.0.6.dist-info/WHEEL
openghg_defs-0.0.6.dist-info/top_level.txt
openghg_defs-0.0.6.dist-info/RECORD
