Metadata-Version: 2.4
Name: openghg_defs
Version: 0.0.6
Summary: Supplementary definition data for OpenGHG
Project-URL: Homepage, https://github.com/openghg/openghg_defs
Project-URL: Bug Tracker, https://github.com/openghg/openghg_defs/issues
Requires-Python: >=3.10
License-File: LICENSE
Dynamic: license-file
